{
"0": {"name":"boolean","isResult":false,"isPrimitive":true},"2": {"name":"Result<null, LangError","isResult":true,"isPrimitive":false,"body":{"ok":{"name":"null","isResult":false,"isPrimitive":true},"err":{"name":"LangError","isResult":false,"isPrimitive":false,"body":{"CouldNotReadInput":null}}}},"3": {"name":"null","isResult":false,"isPrimitive":true},"4": {"name":"LangError","isResult":false,"isPrimitive":false,"body":{"CouldNotReadInput":null}},"5": {"name":"Result<boolean, LangError","isResult":true,"isPrimitive":false,"body":{"ok":{"name":"boolean","isResult":false,"isPrimitive":true},"err":{"name":"LangError","isResult":false,"isPrimitive":false,"body":{"CouldNotReadInput":null}}}},"7": {"name":"Array","isResult":false,"isPrimitive":false,"body":{"0":{"name":"BN","isResult":false,"isPrimitive":true}}},"8": {"name":"BN","isResult":false,"isPrimitive":true}
}